dtools/__init__.py
dtools/__main__.py
dtools/main.py
dtools/util.py
nasops-0.1.2.data/scripts/main.py
nasops-0.1.2.data/scripts/util.py
nasops-0.1.2.dist-info/METADATA
nasops-0.1.2.dist-info/WHEEL
nasops-0.1.2.dist-info/entry_points.txt
nasops-0.1.2.dist-info/top_level.txt
nasops-0.1.2.dist-info/RECORD
