Metadata-Version: 2.1
Name: nasops
Version: 0.1.2
Summary: download_from_nas
Author: yifei.gao, wangyang.zuo
Author-email: yifei.gao@sophgo.com, wangyang.zuo@sophon.com
Requires-Dist: requests
Requires-Dist: tqdm
Requires-Dist: configparser
